{"1":{"trty_pk":1,"trty_name":"SST Initiale","trty_order":1,"certificates":[{"cert_pk": 1, "cert_name": "Sauveteur Secouriste du Travail", "cert_order": 1, "cert_short": "SST", "cert_target": 15, "ttce_duration": 12, "cert_permanentonly": false}, {"cert_pk": 3, "cert_name": "Sensibilisation Défibrillation", "cert_order": 3, "cert_short": "DAE", "cert_target": 30, "ttce_duration": 48, "cert_permanentonly": false}]},"2":{"trty_pk":2,"trty_name":"Renouvellement SST","trty_order":2,"certificates":[{"cert_pk": 1, "cert_name": "Sauveteur Secouriste du Travail", "cert_order": 1, "cert_short": "SST", "cert_target": 15, "ttce_duration": 24, "cert_permanentonly": false}, {"cert_pk": 3, "cert_name": "Sensibilisation Défibrillation", "cert_order": 3, "cert_short": "DAE", "cert_target": 30, "ttce_duration": 48, "cert_permanentonly": false}]},"3":{"trty_pk":3,"trty_name":"Manipulation Extincteurs","trty_order":3,"certificates":[{"cert_pk": 2, "cert_name": "Équipement de Première Intervention", "cert_order": 4, "cert_short": "EPI", "cert_target": 66, "ttce_duration": 36, "cert_permanentonly": false}]},"4":{"trty_pk":4,"trty_name":"Sensibilisation Défibrillation","trty_order":4,"certificates":[{"cert_pk": 3, "cert_name": "Sensibilisation Défibrillation", "cert_order": 3, "cert_short": "DAE", "cert_target": 30, "ttce_duration": 24, "cert_permanentonly": false}]},"5":{"trty_pk":5,"trty_name":"Habilitation Électrique","trty_order":5,"certificates":[{"cert_pk": 4, "cert_name": "Habilitation Électrique", "cert_order": 2, "cert_short": "H0B0", "cert_target": 20, "ttce_duration": 24, "cert_permanentonly": false}]},"6":{"trty_pk":6,"trty_name":"Agent d'Évacuation","trty_order":6,"certificates":[{"cert_pk": 5, "cert_name": "Agent d'Évacuation", "cert_order": 5, "cert_short": "EVAC", "cert_target": 30, "ttce_duration": 12, "cert_permanentonly": false}]},"7":{"trty_pk":7,"trty_name":"Formateur SST Initiale","trty_order":7,"certificates":[{"cert_pk": 1, "cert_name": "Sauveteur Secouriste du Travail", "cert_order": 1, "cert_short": "SST", "cert_target": 15, "ttce_duration": 12, "cert_permanentonly": false}, {"cert_pk": 3, "cert_name": "Sensibilisation Défibrillation", "cert_order": 3, "cert_short": "DAE", "cert_target": 30, "ttce_duration": 48, "cert_permanentonly": false}, {"cert_pk": 6, "cert_name": "Formateur SST", "cert_order": 6, "cert_short": "FSST", "cert_target": 0, "ttce_duration": 12, "cert_permanentonly": false}]},"8":{"trty_pk":8,"trty_name":"Renouvellement Formateur SST","trty_order":8,"certificates":[{"cert_pk": 1, "cert_name": "Sauveteur Secouriste du Travail", "cert_order": 1, "cert_short": "SST", "cert_target": 15, "ttce_duration": 24, "cert_permanentonly": false}, {"cert_pk": 3, "cert_name": "Sensibilisation Défibrillation", "cert_order": 3, "cert_short": "DAE", "cert_target": 30, "ttce_duration": 0, "cert_permanentonly": false}, {"cert_pk": 6, "cert_name": "Formateur SST", "cert_order": 6, "cert_short": "FSST", "cert_target": 0, "ttce_duration": 24, "cert_permanentonly": false}]}}